{"nodes":[{"label":"atomic physics","x":-66.04132080078125,"y":-146.04592895507812,"id":"n8","attributes":{"Type":"context","Description":"Studies that include atomic physics","name":"atomic physics","Frequency":"2","id":"atomic physics","membership":"2.0"},"color":"rgb(154,150,229)","size":10.0},{"label":"mechanics","x":-83.75289916992188,"y":-40.24803924560547,"id":"n2","attributes":{"Type":"context","Description":"Studies that include Newtonian mechanics","name":"mechanics","Frequency":"51","id":"mechanics","membership":"2.0"},"color":"rgb(154,150,229)","size":40.0},{"label":"students\u0027 epistemologies","x":388.8062438964844,"y":16.503204345703125,"id":"n10","attributes":{"Type":"framework","Description":"Examines students’ understanding of the nature of physics, knowledge, role of mathematics etc.","name":"students\u0027 epistemologies","Frequency":"21","id":"students\u0027 epistemologies","membership":"3.0"},"color":"rgb(249,119,67)","size":21.632652282714844},{"label":"problem solving","x":-174.3679962158203,"y":-108.63123321533203,"id":"n17","attributes":{"Type":"framework","Description":"Models the skills, strategies and processes of problem solving.","name":"problem solving","Frequency":"13","id":"problem solving","membership":"2.0"},"color":"rgb(154,150,229)","size":16.73469352722168},{"label":"quantum mechanics","x":87.5892333984375,"y":-78.32889556884766,"id":"n4","attributes":{"Type":"context","Description":"Studies that include quantum mechanics","name":"quantum mechanics","Frequency":"18","id":"quantum mechanics","membership":"2.0"},"color":"rgb(154,150,229)","size":19.795917510986328},{"label":"history of science","x":-1.4038223028182983,"y":-165.56398010253906,"id":"n21","attributes":{"Type":"framework","Description":"Examines historical development of physics to inform education.","name":"history of science","Frequency":"13","id":"history of science","membership":"2.0"},"color":"rgb(154,150,229)","size":16.73469352722168},{"label":"symbolic forms","x":-146.93466186523438,"y":-159.15505981445312,"id":"n24","attributes":{"Type":"framework","Description":"Vocabulary of conceptual schemas associated with mathematical symbols.","name":"symbolic forms","Frequency":"9","id":"symbolic forms","membership":"2.0"},"color":"rgb(154,150,229)","size":14.285715103149414},{"label":"optics","x":-90.41828155517578,"y":-203.08349609375,"id":"n7","attributes":{"Type":"context","Description":"Studies that include optics","name":"optics","Frequency":"3","id":"optics","membership":"2.0"},"color":"rgb(154,150,229)","size":10.612244606018066},{"label":"external representations","x":-99.45712280273438,"y":-120.09088134765625,"id":"n13","attributes":{"Type":"framework","Description":"Views e.g. mathematic symbols as external representations of physics phenomena or concepts.","name":"external representations","Frequency":"7","id":"external representations","membership":"2.0"},"color":"rgb(154,150,229)","size":13.061224937438965},{"label":"electricity and magnetism","x":119.76811218261719,"y":-3.689742088317871,"id":"n1","attributes":{"Type":"context","Description":"Studies that include E\u0026M","name":"electricity and magnetism","Frequency":"40","id":"electricity and magnetism","membership":"2.0"},"color":"rgb(154,150,229)","size":33.26530456542969},{"label":"conceptual blending","x":165.06442260742188,"y":-85.12023162841797,"id":"n20","attributes":{"Type":"framework","Description":"Models cognition as blending of “mental spaces” into a “blended space”.","name":"conceptual blending","Frequency":"6","id":"conceptual blending","membership":"2.0"},"color":"rgb(154,150,229)","size":12.448979377746582},{"label":"resources","x":334.3725891113281,"y":193.14898681640625,"id":"n16","attributes":{"Type":"framework","Description":"A phenomenological model of thinking comprising connected chunk of diverse knowledge elements.","name":"resources","Frequency":"14","id":"resources","membership":"3.0"},"color":"rgb(249,119,67)","size":17.346939086914062},{"label":"general relativity","x":54.09100341796875,"y":24.670461654663086,"id":"n5","attributes":{"Type":"context","Description":"Studies that include general relativity","name":"general relativity","Frequency":"3","id":"general relativity","membership":"2.0"},"color":"rgb(154,150,229)","size":10.612244606018066},{"label":"conceptions","x":-41.50358963012695,"y":107.1698226928711,"id":"n11","attributes":{"Type":"framework","Description":"Describes students’ understanding of e.g. physics concepts.","name":"conceptions","Frequency":"17","id":"conceptions","membership":"2.0"},"color":"rgb(154,150,229)","size":19.183673858642578},{"label":"thermodynamics","x":-115.72500610351562,"y":44.63291549682617,"id":"n3","attributes":{"Type":"context","Description":"Studies that include thermodynamics","name":"thermodynamics","Frequency":"14","id":"thermodynamics","membership":"2.0"},"color":"rgb(154,150,229)","size":17.346939086914062},{"label":"constructivism","x":-10.149266242980957,"y":33.27271270751953,"id":"n9","attributes":{"Type":"framework","Description":"Suggests that learners construct knowledge in connection to their existing knowledge.","name":"constructivism","Frequency":"4","id":"constructivism","membership":"2.0"},"color":"rgb(154,150,229)","size":11.22449016571045},{"label":"ACER","x":286.2617492675781,"y":61.96781539916992,"id":"n22","attributes":{"Type":"framework","Description":"Organizing structure for students’ mathematics use when solving problems.","name":"ACER","Frequency":"6","id":"ACER","membership":"3.0"},"color":"rgb(249,119,67)","size":12.448979377746582},{"label":"science","x":-276.5237731933594,"y":88.087890625,"id":"n0","attributes":{"Type":"context","Description":"Studies that include science generally, not necessarily just physics","name":"science","Frequency":"12","id":"science","membership":"1.0"},"color":"rgb(40,179,106)","size":16.12244987487793},{"label":"modeling","x":-181.15830993652344,"y":-46.187767028808594,"id":"n14","attributes":{"Type":"framework","Description":"Views models as central conceptual structures in physics.","name":"modeling","Frequency":"9","id":"modeling","membership":"2.0"},"color":"rgb(154,150,229)","size":14.285715103149414},{"label":"unclear.context","x":22.56439781188965,"y":209.9793701171875,"id":"n6","attributes":{"Type":"context","Description":"Studies where the topic or context is unclear","name":"unclear.context","Frequency":"13","id":"unclear.context","membership":"2.0"},"color":"rgb(154,150,229)","size":16.73469352722168},{"label":"achievement","x":-362.7999572753906,"y":129.47012329101562,"id":"n15","attributes":{"Type":"framework","Description":"Looks at outcomes of learning as measured by concept tests, and their correlations.","name":"achievement","Frequency":"9","id":"achievement","membership":"1.0"},"color":"rgb(40,179,106)","size":14.285715103149414},{"label":"other.framework","x":3.1842517852783203,"y":-88.9561767578125,"id":"n18","attributes":{"Type":"framework","Description":"Frameworks with ≤ 3 mentions.","name":"other.framework","Frequency":"36","id":"other.framework","membership":"2.0"},"color":"rgb(154,150,229)","size":30.816328048706055},{"label":"unclear.framework","x":103.18434143066406,"y":137.7480926513672,"id":"n23","attributes":{"Type":"framework","Description":"Studies in which the theoretical framework is unclear","name":"unclear.framework","Frequency":"9","id":"unclear.framework","membership":"2.0"},"color":"rgb(154,150,229)","size":14.285715103149414}],"edges":[{"source":"n10","target":"n22","id":"36","attributes":{},"color":"rgb(249,119,67)","size":4.0},{"source":"n1","target":"n23","id":"8","attributes":{},"color":"rgb(154,150,229)","size":3.0},{"source":"n2","target":"n24","id":"23","attributes":{},"color":"rgb(154,150,229)","size":6.0},{"source":"n4","target":"n18","id":"27","attributes":{},"color":"rgb(154,150,229)","size":10.0},{"source":"n2","target":"n13","id":"18","attributes":{},"color":"rgb(154,150,229)","size":5.0},{"source":"n2","target":"n14","id":"19","attributes":{},"color":"rgb(154,150,229)","size":6.0},{"source":"n1","target":"n20","id":"6","attributes":{},"color":"rgb(154,150,229)","size":3.0},{"source":"n10","target":"n16","id":"35","attributes":{},"color":"rgb(249,119,67)","size":10.0},{"source":"n4","target":"n5","id":"26","attributes":{},"color":"rgb(154,150,229)","size":2.0},{"source":"n3","target":"n18","id":"25","attributes":{},"color":"rgb(154,150,229)","size":5.0},{"source":"n16","target":"n22","id":"39","attributes":{},"color":"rgb(249,119,67)","size":4.0},{"source":"n1","target":"n9","id":"4","attributes":{},"color":"rgb(154,150,229)","size":2.0},{"source":"n2","target":"n3","id":"11","attributes":{},"color":"rgb(154,150,229)","size":5.0},{"source":"n0","target":"n15","id":"1","attributes":{},"color":"rgb(40,179,106)","size":6.0},{"source":"n2","target":"n8","id":"14","attributes":{},"color":"rgb(154,150,229)","size":2.0},{"source":"n2","target":"n9","id":"15","attributes":{},"color":"rgb(154,150,229)","size":2.0},{"source":"n2","target":"n11","id":"16","attributes":{},"color":"rgb(154,150,229)","size":9.0},{"source":"n5","target":"n9","id":"30","attributes":{},"color":"rgb(154,150,229)","size":2.0},{"source":"n2","target":"n17","id":"20","attributes":{},"color":"rgb(154,150,229)","size":6.0},{"source":"n6","target":"n11","id":"31","attributes":{},"color":"rgb(154,150,229)","size":4.0},{"source":"n1","target":"n2","id":"2","attributes":{},"color":"rgb(154,150,229)","size":13.0},{"source":"n1","target":"n22","id":"7","attributes":{},"color":"rgb(201,134,148)","size":4.0},{"source":"n2","target":"n5","id":"12","attributes":{},"color":"rgb(154,150,229)","size":2.0},{"source":"n2","target":"n18","id":"21","attributes":{},"color":"rgb(154,150,229)","size":13.0},{"source":"n1","target":"n5","id":"3","attributes":{},"color":"rgb(154,150,229)","size":2.0},{"source":"n2","target":"n7","id":"13","attributes":{},"color":"rgb(154,150,229)","size":3.0},{"source":"n6","target":"n23","id":"32","attributes":{},"color":"rgb(154,150,229)","size":3.0},{"source":"n8","target":"n18","id":"33","attributes":{},"color":"rgb(154,150,229)","size":2.0},{"source":"n2","target":"n21","id":"22","attributes":{},"color":"rgb(154,150,229)","size":5.0}]}